robothub_depthai/__init__.py
robothub_depthai/app.py
robothub_depthai/callbacks.py
robothub_depthai/hub_camera.py
robothub_depthai/manager.py
robothub_depthai/utils.py
robothub_depthai-0.2.2.dist-info/LICENSE
robothub_depthai-0.2.2.dist-info/METADATA
robothub_depthai-0.2.2.dist-info/WHEEL
robothub_depthai-0.2.2.dist-info/top_level.txt
robothub_depthai-0.2.2.dist-info/RECORD
