Metadata-Version: 2.1
Name: robothub_depthai
Version: 0.2.2
Summary: RobotHub-DepthAI integration library
Home-page: https://www.luxonis.com/
Author: Luxonis
Author-email: support@luxonis.com
License: MIT
Project-URL: Homepage, https://github.com/luxonis/robothub-depthai/
Project-URL: Documentation, https://hub-docs.luxonis.com/
Keywords: robothub robot hub connect agent depthai sdk
Classifier: Development Status :: 3 - Alpha
Classifier: Intended Audience :: Developers
Classifier: Intended Audience :: Education
Classifier: Intended Audience :: Information Technology
Classifier: Intended Audience :: Science/Research
Classifier: Programming Language :: Python
Classifier: Programming Language :: Python :: 3.10
Classifier: License :: OSI Approved :: MIT License
Classifier: Operating System :: Unix
Classifier: Topic :: Software Development
Classifier: Topic :: Scientific/Engineering
License-File: LICENSE
